GaiaAlertsPy/__init__.py
GaiaAlertsPy/alert.py
GaiaAlertsPy/history.py
GaiaAlertsPy/plotting.py
docs/__init__.py
docs/source/__init__.py
docs/source/conf.py
GaiaAlertsPy-1.0.0.dist-info/LICENSE.rst
GaiaAlertsPy-1.0.0.dist-info/METADATA
GaiaAlertsPy-1.0.0.dist-info/WHEEL
GaiaAlertsPy-1.0.0.dist-info/top_level.txt
GaiaAlertsPy-1.0.0.dist-info/RECORD
